.gitignore
CHANGES.txt
INSTALL.txt
README.txt
bootstrap.py
buildout.cfg
setup.py
src/sterch/__init__.py
src/sterch.queue.egg-info/PKG-INFO
src/sterch.queue.egg-info/SOURCES.txt
src/sterch.queue.egg-info/dependency_links.txt
src/sterch.queue.egg-info/namespace_packages.txt
src/sterch.queue.egg-info/requires.txt
src/sterch.queue.egg-info/top_level.txt
src/sterch/queue/README.txt
src/sterch/queue/__init__.py
src/sterch/queue/configure.zcml
src/sterch/queue/interfaces.py
src/sterch/queue/meta.zcml
src/sterch/queue/metaconfigure.py
src/sterch/queue/metadirectives.py
src/sterch/queue/tests/__init__.py
src/sterch/queue/tests/test_classes_objects.py
src/sterch/queue/tests/test_queue_directive.py